full_adder/full_adder.vhd
library ieee;
use ieee.std_logic_1164.all;

entity full_adder is
  port (
    a     : in std_logic;
    b     : in std_logic;
    c_i   : in std_logic;
    s     : out std_logic;
    c_o   : out std_logic
  ) ;
end full_adder;

architecture rtl of full_adder is
begin
    process(a,b,c_i) is
    begin
      s <= (a xor b) xor c_i;
      c_o <= (a and b) or ((a xor b) and c_i);
    end process;
end rtl  ; -- rtl

full_adder/full_adder_tb.vhd
library ieee;
use ieee.std_logic_1164.all;

entity full_adder_tb is
end full_adder_tb;

architecture tb of full_adder_tb is
component full_adder is
    port (
        a     : in std_logic;
        b     : in std_logic;
        c_i   : in std_logic;
        s     : out std_logic;
        c_o   : out std_logic
    ) ;
end component;
signal a_in, b_in, c_in, s_out, c_out : std_logic;
begin
    dut: full_adder port map(a=>a_in, b=>b_in, c_i=>c_in, s=>s_out, c_o=>c_out);
    process
    begin
        a_in <= '0';
        b_in <= '0';
        c_in <= '0';
        wait for 1 ns;
        assert(s_out='0' and c_out='0') report "Erro em 0+0 | 0" severity error;

        a_in <= '0';
        b_in <= '0';
        c_in <= '1';
        wait for 1 ns;
        assert(s_out='1' and c_out='0') report "Erro em 0+0 | 1" severity error;

        a_in <= '0';
        b_in <= '1';
        c_in <= '0';
        wait for 1 ns;
        assert(s_out='1' and c_out='0') report "Erro em 0+1 | 0" severity error;

        a_in <= '0';
        b_in <= '1';
        c_in <= '1';
        wait for 1 ns;
        assert(s_out='0' and c_out='1') report "Erro em 0+1 | 1" severity error;

        a_in <= '1';
        b_in <= '0';
        c_in <= '0';
        wait for 1 ns;
        assert(s_out='1' and c_out='0') report "Erro em 1+0 | 0" severity error;

        a_in <= '1';
        b_in <= '0';
        c_in <= '1';
        wait for 1 ns;
        assert(s_out='0' and c_out='1') report "Erro em 1+0 | 1" severity error;

        a_in <= '1';
        b_in <= '1';
        c_in <= '0';
        wait for 1 ns;
        assert(s_out='0' and c_out='1') report "Erro em 1+1 | 0" severity error;

        a_in <= '1';
        b_in <= '1';
        c_in <= '1';
        wait for 1 ns;
        assert(s_out='1' and c_out='1') report "Erro em 1+1 | 1" severity error;

        assert(false) report "Testes realizados com sucesso" severity note;
        wait;
    end process;
end tb  ; -- tb

full_adder/wave.vcd
$date
  Wed Aug 26 13:25:39 2020
$end
$version
  GHDL v0
$end
$timescale
  1 fs
$end
$scope module standard $end
$upscope $end
$scope module std_logic_1164 $end
$upscope $end
$scope module full_adder_tb $end
$var reg 1 ! a_in $end
$var reg 1 " b_in $end
$var reg 1 # c_in $end
$var reg 1 $ s_out $end
$var reg 1 % c_out $end
$scope module dut $end
$var reg 1 & a $end
$var reg 1 ' b $end
$var reg 1 ( c_i $end
$var reg 1 ) s $end
$var reg 1 * c_o $end
$upscope $end
$upscope $end
$enddefinitions $end
#0
0!
0"
0#
0$
0%
0&
0'
0(
0)
0*
#1000000
1#
1$
1(
1)
#2000000
1"
0#
1'
0(
#3000000
1#
0$
1%
1(
0)
1*
#4000000
1!
0"
0#
1$
0%
1&
0'
0(
1)
0*
#5000000
1#
0$
1%
1(
0)
1*
#6000000
1"
0#
1'
0(
#7000000
1#
1$
1(
1)
